sphinxwrapper/__init__.py
sphinxwrapper/config.py
sphinxwrapper/pocketsphinx_wrap.py
sphinxwrapper-1.3.0.dist-info/LICENSE
sphinxwrapper-1.3.0.dist-info/METADATA
sphinxwrapper-1.3.0.dist-info/WHEEL
sphinxwrapper-1.3.0.dist-info/top_level.txt
sphinxwrapper-1.3.0.dist-info/RECORD
